[
   {
      "descricao":"Idade",
      "objetivo":null,
      "valorCrisp":22.0,
      "universo":{
         "inicio":0,
         "fim":90
      },
      "valorDeffuzificado":0.0,
      "termos":[
         {
            "descricao":"Jovem",
            "suporte":{
               "inicio":0,
               "fim":30
            },
            "nucleo":{
               "inicio":0,
               "fim":20
            },
            "condicoes":[

            ],
            "valorFuzzificado":0.8,
            "valorAtivacao":0.0,
            "quantidadeDeValoresDoUniverso":0
         },
         {
            "descricao":"Adulto",
            "suporte":{
               "inicio":20,
               "fim":60
            },
            "nucleo":{
               "inicio":30,
               "fim":50
            },
            "condicoes":[

            ],
            "valorFuzzificado":0.2,
            "valorAtivacao":0.0,
            "quantidadeDeValoresDoUniverso":0
         },
         {
            "descricao":"Idoso",
            "suporte":{
               "inicio":50,
               "fim":90
            },
            "nucleo":{
               "inicio":60,
               "fim":90
            },
            "condicoes":[

            ],
            "valorFuzzificado":0.0,
            "valorAtivacao":0.0,
            "quantidadeDeValoresDoUniverso":0
         }
      ]
   },
   {
      "descricao":"Frequencia",
      "objetivo":null,
      "valorCrisp":135.0,
      "universo":{
         "inicio":50,
         "fim":200
      },
      "valorDeffuzificado":0.0,
      "termos":[
         {
            "descricao":"Baixa",
            "suporte":{
               "inicio":50,
               "fim":90
            },
            "nucleo":{
               "inicio":50,
               "fim":70
            },
            "condicoes":[

            ],
            "valorFuzzificado":0.0,
            "valorAtivacao":0.0,
            "quantidadeDeValoresDoUniverso":0
         },
         {
            "descricao":"Moderada",
            "suporte":{
               "inicio":70,
               "fim":140
            },
            "nucleo":{
               "inicio":90,
               "fim":120
            },
            "condicoes":[

            ],
            "valorFuzzificado":0.25,
            "valorAtivacao":0.0,
            "quantidadeDeValoresDoUniverso":0
         },
         {
            "descricao":"Alta",
            "suporte":{
               "inicio":120,
               "fim":200
            },
            "nucleo":{
               "inicio":140,
               "fim":200
            },
            "condicoes":[

            ],
            "valorFuzzificado":0.75,
            "valorAtivacao":0.0,
            "quantidadeDeValoresDoUniverso":0
         }
      ]
   },
   {
      "descricao":"Potencia",
      "objetivo":"Sim",
      "valorCrisp":0.0,
      "universo":{
         "inicio":0,
         "fim":100
      },
      "valorDeffuzificado":49.84615384615385,
      "termos":[
         {
            "descricao":"Minima",
            "suporte":{
               "inicio":0,
               "fim":30
            },
            "nucleo":{
               "inicio":0,
               "fim":10
            },
            "condicoes":[

            ],
            "valorFuzzificado":0.0,
            "valorAtivacao":0.0,
            "quantidadeDeValoresDoUniverso":3
         },
         {
            "descricao":"Media",
            "suporte":{
               "inicio":10,
               "fim":70
            },
            "nucleo":{
               "inicio":30,
               "fim":50
            },
            "condicoes":[
               {
                  "variavel":{
                     "descricao":"Idade",
                     "objetivo":null,
                     "valorCrisp":22.0,
                     "universo":{
                        "inicio":0,
                        "fim":90
                     },
                     "valorDeffuzificado":0.0,
                     "termos":[
                        {
                           "descricao":"Jovem",
                           "suporte":{
                              "inicio":0,
                              "fim":30
                           },
                           "nucleo":{
                              "inicio":0,
                              "fim":20
                           },
                           "condicoes":[

                           ],
                           "valorFuzzificado":0.0,
                           "valorAtivacao":0.0,
                           "quantidadeDeValoresDoUniverso":0
                        },
                        {
                           "descricao":"Adulto",
                           "suporte":{
                              "inicio":20,
                              "fim":60
                           },
                           "nucleo":{
                              "inicio":30,
                              "fim":50
                           },
                           "condicoes":[

                           ],
                           "valorFuzzificado":0.0,
                           "valorAtivacao":0.0,
                           "quantidadeDeValoresDoUniverso":0
                        },
                        {
                           "descricao":"Idoso",
                           "suporte":{
                              "inicio":50,
                              "fim":90
                           },
                           "nucleo":{
                              "inicio":60,
                              "fim":90
                           },
                           "condicoes":[

                           ],
                           "valorFuzzificado":0.0,
                           "valorAtivacao":0.0,
                           "quantidadeDeValoresDoUniverso":0
                        }
                     ]
                  },
                  "termo":{
                     "descricao":"Jovem",
                     "suporte":{
                        "inicio":0,
                        "fim":30
                     },
                     "nucleo":{
                        "inicio":0,
                        "fim":20
                     },
                     "condicoes":[

                     ],
                     "valorFuzzificado":0.0,
                     "valorAtivacao":0.0,
                     "quantidadeDeValoresDoUniverso":0
                  }
               },
               {
                  "variavel":{
                     "descricao":"Frequencia",
                     "objetivo":null,
                     "valorCrisp":135.0,
                     "universo":{
                        "inicio":50,
                        "fim":200
                     },
                     "valorDeffuzificado":0.0,
                     "termos":[
                        {
                           "descricao":"Baixa",
                           "suporte":{
                              "inicio":50,
                              "fim":90
                           },
                           "nucleo":{
                              "inicio":50,
                              "fim":70
                           },
                           "condicoes":[

                           ],
                           "valorFuzzificado":0.0,
                           "valorAtivacao":0.0,
                           "quantidadeDeValoresDoUniverso":0
                        },
                        {
                           "descricao":"Moderada",
                           "suporte":{
                              "inicio":70,
                              "fim":140
                           },
                           "nucleo":{
                              "inicio":90,
                              "fim":120
                           },
                           "condicoes":[

                           ],
                           "valorFuzzificado":0.0,
                           "valorAtivacao":0.0,
                           "quantidadeDeValoresDoUniverso":0
                        },
                        {
                           "descricao":"Alta",
                           "suporte":{
                              "inicio":120,
                              "fim":200
                           },
                           "nucleo":{
                              "inicio":140,
                              "fim":200
                           },
                           "condicoes":[

                           ],
                           "valorFuzzificado":0.0,
                           "valorAtivacao":0.0,
                           "quantidadeDeValoresDoUniverso":0
                        }
                     ]
                  },
                  "termo":{
                     "descricao":"Alta",
                     "suporte":{
                        "inicio":120,
                        "fim":200
                     },
                     "nucleo":{
                        "inicio":140,
                        "fim":200
                     },
                     "condicoes":[

                     ],
                     "valorFuzzificado":0.0,
                     "valorAtivacao":0.0,
                     "quantidadeDeValoresDoUniverso":0
                  }
               }
            ],
            "valorFuzzificado":0.0,
            "valorAtivacao":0.75,
            "quantidadeDeValoresDoUniverso":3
         },
         {
            "descricao":"Maxima",
            "suporte":{
               "inicio":50,
               "fim":100
            },
            "nucleo":{
               "inicio":70,
               "fim":100
            },
            "condicoes":[
               {
                  "variavel":{
                     "descricao":"Idade",
                     "objetivo":null,
                     "valorCrisp":22.0,
                     "universo":{
                        "inicio":0,
                        "fim":90
                     },
                     "valorDeffuzificado":0.0,
                     "termos":[
                        {
                           "descricao":"Jovem",
                           "suporte":{
                              "inicio":0,
                              "fim":30
                           },
                           "nucleo":{
                              "inicio":0,
                              "fim":20
                           },
                           "condicoes":[

                           ],
                           "valorFuzzificado":0.0,
                           "valorAtivacao":0.0,
                           "quantidadeDeValoresDoUniverso":0
                        },
                        {
                           "descricao":"Adulto",
                           "suporte":{
                              "inicio":20,
                              "fim":60
                           },
                           "nucleo":{
                              "inicio":30,
                              "fim":50
                           },
                           "condicoes":[

                           ],
                           "valorFuzzificado":0.0,
                           "valorAtivacao":0.0,
                           "quantidadeDeValoresDoUniverso":0
                        },
                        {
                           "descricao":"Idoso",
                           "suporte":{
                              "inicio":50,
                              "fim":90
                           },
                           "nucleo":{
                              "inicio":60,
                              "fim":90
                           },
                           "condicoes":[

                           ],
                           "valorFuzzificado":0.0,
                           "valorAtivacao":0.0,
                           "quantidadeDeValoresDoUniverso":0
                        }
                     ]
                  },
                  "termo":{
                     "descricao":"Adulto",
                     "suporte":{
                        "inicio":20,
                        "fim":60
                     },
                     "nucleo":{
                        "inicio":30,
                        "fim":50
                     },
                     "condicoes":[

                     ],
                     "valorFuzzificado":0.0,
                     "valorAtivacao":0.0,
                     "quantidadeDeValoresDoUniverso":0
                  }
               },
               {
                  "variavel":{
                     "descricao":"Frequencia",
                     "objetivo":null,
                     "valorCrisp":135.0,
                     "universo":{
                        "inicio":50,
                        "fim":200
                     },
                     "valorDeffuzificado":0.0,
                     "termos":[
                        {
                           "descricao":"Baixa",
                           "suporte":{
                              "inicio":50,
                              "fim":90
                           },
                           "nucleo":{
                              "inicio":50,
                              "fim":70
                           },
                           "condicoes":[

                           ],
                           "valorFuzzificado":0.0,
                           "valorAtivacao":0.0,
                           "quantidadeDeValoresDoUniverso":0
                        },
                        {
                           "descricao":"Moderada",
                           "suporte":{
                              "inicio":70,
                              "fim":140
                           },
                           "nucleo":{
                              "inicio":90,
                              "fim":120
                           },
                           "condicoes":[

                           ],
                           "valorFuzzificado":0.0,
                           "valorAtivacao":0.0,
                           "quantidadeDeValoresDoUniverso":0
                        },
                        {
                           "descricao":"Alta",
                           "suporte":{
                              "inicio":120,
                              "fim":200
                           },
                           "nucleo":{
                              "inicio":140,
                              "fim":200
                           },
                           "condicoes":[

                           ],
                           "valorFuzzificado":0.0,
                           "valorAtivacao":0.0,
                           "quantidadeDeValoresDoUniverso":0
                        }
                     ]
                  },
                  "termo":{
                     "descricao":"Moderada",
                     "suporte":{
                        "inicio":70,
                        "fim":140
                     },
                     "nucleo":{
                        "inicio":90,
                        "fim":120
                     },
                     "condicoes":[

                     ],
                     "valorFuzzificado":0.0,
                     "valorAtivacao":0.0,
                     "quantidadeDeValoresDoUniverso":0
                  }
               }
            ],
            "valorFuzzificado":0.0,
            "valorAtivacao":0.2,
            "quantidadeDeValoresDoUniverso":5
         }
      ]
   }
]